pfsc_util/__init__.py
pfsc_util/imports.py
pfsc_util/scan.py
pfsc_util-0.22.8.dist-info/LICENSE
pfsc_util-0.22.8.dist-info/METADATA
pfsc_util-0.22.8.dist-info/NOTICE
pfsc_util-0.22.8.dist-info/WHEEL
pfsc_util-0.22.8.dist-info/top_level.txt
pfsc_util-0.22.8.dist-info/RECORD
