Metadata-Version: 2.1
Name: pfsc-util
Version: 0.22.8
Summary: Proofscape Utilities
Home-page: https://github.com/proofscape/pfsc-util
License: Apache 2.0
Platform: UNKNOWN
Classifier: License :: OSI Approved :: Apache Software License
Classifier: Operating System :: OS Independent
Classifier: Programming Language :: Python :: 3
